ftllm/__init__.py
ftllm/chat.py
ftllm/cli.py
ftllm/download.py
ftllm/export.py
ftllm/hf_model.py
ftllm/libfastllm_tools-cpu.so
ftllm/libfastllm_tools-cu11.so
ftllm/libfastllm_tools.so
ftllm/libnuma.so.1
ftllm/llm.py
ftllm/server.py
ftllm/torch2flm.py
ftllm/ui.py
ftllm/util.py
ftllm/web_demo.py
ftllm/webui.py
ftllm/openai_server/fastllm_completion.py
ftllm/openai_server/fastllm_embed.py
ftllm/openai_server/fastllm_model.py
ftllm/openai_server/fastllm_reranker.py
ftllm/openai_server/protocal/openai_protocol.py
ftllm/openai_server/tool_parsers/__init__.py
ftllm/openai_server/tool_parsers/abstract_tool_parser.py
ftllm/openai_server/tool_parsers/deepseekv31_tool_parser.py
ftllm/openai_server/tool_parsers/deepseekv3_tool_parser.py
ftllm/openai_server/tool_parsers/glm4_moe_tool_parser.py
ftllm/openai_server/tool_parsers/granite_20b_fc_tool_parser.py
ftllm/openai_server/tool_parsers/granite_tool_parser.py
ftllm/openai_server/tool_parsers/hermes_tool_parser.py
ftllm/openai_server/tool_parsers/hunyuan_a13b_tool_parser.py
ftllm/openai_server/tool_parsers/internlm2_tool_parser.py
ftllm/openai_server/tool_parsers/jamba_tool_parser.py
ftllm/openai_server/tool_parsers/kimi_k2_tool_parser.py
ftllm/openai_server/tool_parsers/llama4_pythonic_tool_parser.py
ftllm/openai_server/tool_parsers/llama_tool_parser.py
ftllm/openai_server/tool_parsers/minimax_tool_parser.py
ftllm/openai_server/tool_parsers/mistral_tool_parser.py
ftllm/openai_server/tool_parsers/phi4mini_tool_parser.py
ftllm/openai_server/tool_parsers/pythonic_tool_parser.py
ftllm/openai_server/tool_parsers/qwen3coder_tool_parser.py
ftllm/openai_server/tool_parsers/step3_tool_parser.py
ftllm/openai_server/tool_parsers/utils.py
ftllm/openai_server/tool_parsers/xlam_tool_parser.py
ftllm-0.1.5.1.dist-info/METADATA
ftllm-0.1.5.1.dist-info/WHEEL
ftllm-0.1.5.1.dist-info/entry_points.txt
ftllm-0.1.5.1.dist-info/top_level.txt
ftllm-0.1.5.1.dist-info/RECORD
